LICENSE.txt
setup.cfg
setup.py
gin/__init__.py
gin/config.py
gin/config_parser.py
gin/resource_reader.py
gin/selector_map.py
gin/utils.py
gin/testdata/__init__.py
gin/testdata/dynamic_registration.py
gin/testdata/import_test_configurables.py
gin/testdata/invalid_import.py
gin/testdata/fake_package/__init__.py
gin/testdata/fake_package/fake_gin_package/__init__.py
gin/testdata/fake_package/fake_gin_package/config/__init__.py
gin/tf/__init__.py
gin/tf/external_configurables.py
gin/tf/utils.py
gin/torch/__init__.py
gin/torch/external_configurables.py
gin_config_v2.egg-info/PKG-INFO
gin_config_v2.egg-info/SOURCES.txt
gin_config_v2.egg-info/dependency_links.txt
gin_config_v2.egg-info/requires.txt
gin_config_v2.egg-info/top_level.txt