Metadata-Version: 2.1
Name: gin-config-v2
Version: 0.8.0
Summary: Gin-Config: A lightweight configuration library for Python
Home-page: https://github.com/google/gin-config
Author: The Gin-Config Team
License: Apache 2.0
Project-URL: Documentation, https://github.com/google/gin-config/docs
Project-URL: Bug Reports, https://github.com/google/gin-config/issues
Project-URL: Source, https://github.com/google/gin-config
Keywords: gin-config gin python configuration machine learning
Classifier: Development Status :: 3 - Alpha
Classifier: Intended Audience :: Developers
Classifier: Intended Audience :: Education
Classifier: Intended Audience :: Science/Research
Classifier: License :: OSI Approved :: Apache Software License
Classifier: Programming Language :: Python :: 3
Classifier: Programming Language :: Python :: 3.7
Classifier: Programming Language :: Python :: 3.8
Classifier: Programming Language :: Python :: 3.9
Classifier: Programming Language :: Python :: 3.10
Classifier: Programming Language :: Python :: 3.11
Classifier: Programming Language :: Python :: 3.12
Classifier: Programming Language :: Python :: 3.13
Classifier: Programming Language :: Python :: 3.14
Classifier: Topic :: Scientific/Engineering
Classifier: Topic :: Scientific/Engineering :: Mathematics
Classifier: Topic :: Scientific/Engineering :: Artificial Intelligence
Classifier: Topic :: Software Development
Classifier: Topic :: Software Development :: Libraries
Classifier: Topic :: Software Development :: Libraries :: Python Modules
Requires-Python: >=3.7
License-File: LICENSE.txt
Provides-Extra: tensorflow
Requires-Dist: tensorflow>=2.0.0; extra == "tensorflow"
Provides-Extra: tensorflow-gpu
Requires-Dist: tensorflow-gpu>=2.0.0; extra == "tensorflow-gpu"
Provides-Extra: tf-nightly
Requires-Dist: tf-nightly; extra == "tf-nightly"
Provides-Extra: torch
Requires-Dist: torch>=1.13.0; extra == "torch"
Provides-Extra: pytorch-nightly
Requires-Dist: pytorch-nightly; extra == "pytorch-nightly"
Provides-Extra: testing
Requires-Dist: absl-py>=0.1.6; extra == "testing"
Requires-Dist: mock>=3.0.5; extra == "testing"
Requires-Dist: pytest; extra == "testing"
